[
    {
        "fileName": "1.jpg",
        "title": "heaven of time",
        "desc": "here is the heaven of time"
    },
    {
        "fileName": "2.jpg",
        "title": "heaven of time",
        "desc": "here is the heaven of time"
    },
    {
        "fileName": "3.jpg",
        "title": "heaven of time",
        "desc": "here is the heaven of time"
    },
    {
        "fileName": "4.jpg",
        "title": "heaven of time",
        "desc": "here is the heaven of time"
    },
    {
        "fileName": "5.jpg",
        "title": "heaven of time",
        "desc": "here is the heaven of time"
    },
    {
        "fileName": "6.jpg",
        "title": "heaven of time",
        "desc": "here is the heaven of time"
    },
    {
        "fileName": "7.jpg",
        "title": "heaven of time",
        "desc": "here is the heaven of time"
    },
    {
        "fileName": "8.jpg",
        "title": "heaven of time",
        "desc": "here is the heaven of time"
    },
    {
        "fileName": "9.jpg",
        "title": "heaven of time",
        "desc": "here is the heaven of time"
    },
    {
        "fileName": "10.jpg",
        "title": "heaven of time",
        "desc": "here is the heaven of time"
    },
    {
        "fileName": "11.jpg",
        "title": "heaven of time",
        "desc": "here is the heaven of time"
    },
    {
        "fileName": "12.jpg",
        "title": "heaven of time",
        "desc": "here is the heaven of time"
    },
    {
        "fileName": "13.jpg",
        "title": "heaven of time",
        "desc": "here is the heaven of time"
    },
    {
        "fileName": "14.jpg",
        "title": "heaven of time",
        "desc": "here is the heaven of time"
    },
    {
        "fileName": "15.jpg",
        "title": "heaven of time",
        "desc": "here is the heaven of time"
    },
    {
        "fileName": "16.jpg",
        "title": "heaven of time",
        "desc": "here is the heaven of time"
    }
]
